[
 {
  "title": "여름의 책",
  "original": "Sommarboken",
  "author": "토베 얀손",
  "country": "핀란드",
  "genre": "문학소설",
  "year": "1972",
  "why": "섬에서 함께 여름을 나는 할머니와 손녀의 조용한 나날. 절제된 문장 속에서 삶과 죽음, 관계의 온기를 길어 올리는 북유럽 '국민소설'. 키건의 고요함을 사랑하는 당신에게.",
  "connect": "맡겨진 소녀, 이처럼 사소한 것들"
 },
 {
  "title": "침묵",
  "original": "沈黙",
  "author": "엔도 슈사쿠",
  "country": "일본",
  "genre": "가톨릭 문학소설",
  "year": "1966",
  "why": "박해 속 신의 침묵을 묻는 가톨릭 실존 소설. 고백록과 신앙 에세이를 즐기는 영성의 독자에게 정면으로 가닿는 질문서.",
  "connect": "고백록, 카뮈 디 에센셜"
 },
 {
  "title": "바르도의 링컨",
  "original": "Lincoln in the Bardo",
  "author": "조지 손더스",
  "country": "미국",
  "genre": "실험 문학소설",
  "year": "2017",
  "why": "죽은 아들 곁을 떠도는 영혼들의 합창으로 쓰인 슬픔의 소설. 서정적 문체와 죽음·내면을 향한 당신 취향의 정점.",
  "connect": "길리아드, 환희의 인간"
 },
 {
  "title": "홈",
  "original": "Home",
  "author": "메릴린 로빈슨",
  "country": "미국",
  "genre": "문학소설",
  "year": "2008",
  "why": "이미 읽은 길리아드와 같은 마을을 비추는 자매편. 용서와 귀향을 다룬 고요하고 깊은 미국 문학.",
  "connect": "길리아드"
 },
 {
  "title": "의식의 강",
  "original": "The River of Consciousness",
  "author": "올리버 색스",
  "country": "영국",
  "genre": "과학 에세이",
  "year": "2017",
  "why": "기억·진화·마음을 문학적 문장으로 풀어낸 '의학계의 계관시인'의 유작. 로벨리식 서정적 과학교양을 사랑하는 독자에게.",
  "connect": "모든 순간의 물리학, 다시 책으로"
 },
 {
  "title": "A가 X에게",
  "original": "From A to X",
  "author": "존 버거",
  "country": "영국",
  "genre": "서간 소설",
  "year": "2008",
  "why": "옥에 갇힌 연인에게 보내는 편지로 쓴 사랑과 저항의 소설. 절제된 문체와 깊은 정서를 좋아하는 당신에게 새로운 형식의 울림.",
  "connect": "이처럼 사소한 것들, 그리움의 정원에서"
 },
 {
  "title": "솔라리스",
  "original": "Solaris",
  "author": "스타니스와프 렘",
  "country": "폴란드",
  "genre": "문학 SF",
  "year": "1961",
  "why": "이해 불가능한 외계 지성 앞에서 인간 내면이 드러나는 사변 SF의 고전. 르 귄·테드 창식 '인간적인 SF'의 원류격 작품.",
  "connect": "어둠의 왼손, 당신 인생의 이야기"
 },
 {
  "title": "여름은 오래 그곳에 남아",
  "original": "火山のふもとで",
  "author": "마쓰이에 마사시",
  "country": "일본",
  "genre": "문학소설",
  "year": "2012",
  "why": "여름 산장의 건축 사무소를 배경으로 시간과 상실을 잔잔히 그린 정밀한 소설. 키건식 절제와 단단한 고요함을 닮은 일본 문학.",
  "connect": "맡겨진 소녀, 푸른 들판을 걷다"
 },
 {
  "title": "브루클린",
  "original": "Brooklyn",
  "author": "콜럼 토빈",
  "country": "아일랜드",
  "genre": "문학소설",
  "year": "2009",
  "why": "1950년대 아일랜드를 떠나 뉴욕으로 향한 소녀의 이야기. 클레어 키건으로 사랑하게 된 아일랜드 문학의 또 다른 결.",
  "connect": "이처럼 사소한 것들, 너무 늦은 시간"
 },
 {
  "title": "뼛속까지 내려가서 써라",
  "original": "Writing Down the Bones",
  "author": "나탈리 골드버그",
  "country": "미국",
  "genre": "글쓰기 에세이",
  "year": "1986",
  "why": "선(禪)과 글쓰기를 잇는 고전적 글쓰기 안내서. '쓰기 위해 읽는' 당신의 독서 DNA에 정확히 맞닿는 책.",
  "connect": "다시 책으로, 글쓰기에 대하여"
 }
]